qihoo_for_t/Test.py
qihoo_for_t/__init__.py
qihoo_for_t/pymongo.py
qihoo_for_t-0.0.dist-info/METADATA
qihoo_for_t-0.0.dist-info/WHEEL
qihoo_for_t-0.0.dist-info/top_level.txt
qihoo_for_t-0.0.dist-info/RECORD
