Metadata-Version: 2.1
Name: qihoo-for-t
Version: 0.0
Summary: test
Home-page: UNKNOWN
Author: lee
Author-email: test@qq.com
License: LGPLv3
Platform: UNKNOWN
Requires-Dist: numpy
